Metadata-Version: 1.0
Name: gopeng
Version: 0.0.1
Summary: Pythonic RapidAPI calls
Home-page: https://github.com/alvations/gopeng
Author: UNKNOWN
Author-email: UNKNOWN
License: UNKNOWN
Platform: UNKNOWN
